{
	"textures": [
		{
			"image": "ogre.png",
			"format": "RGBA8888",
			"size": {
				"w": 18,
				"h": 245
			},
			"scale": 1,
			"frames": [
				{
					"filename": "tower-296.png",
					"rotated": false,
					"trimmed": false,
					"sourceSize": {
						"w": 16,
						"h": 16
					},
					"spriteSourceSize": {
						"x": 0,
						"y": 0,
						"w": 16,
						"h": 16
					},
					"frame": {
						"x": 1,
						"y": 1,
						"w": 16,
						"h": 16
					}
				},
				{
					"filename": "tower-299.png",
					"rotated": false,
					"trimmed": false,
					"sourceSize": {
						"w": 16,
						"h": 16
					},
					"spriteSourceSize": {
						"x": 0,
						"y": 0,
						"w": 16,
						"h": 16
					},
					"frame": {
						"x": 1,
						"y": 1,
						"w": 16,
						"h": 16
					}
				},
				{
					"filename": "tower-300.png",
					"rotated": false,
					"trimmed": false,
					"sourceSize": {
						"w": 16,
						"h": 16
					},
					"spriteSourceSize": {
						"x": 0,
						"y": 0,
						"w": 16,
						"h": 16
					},
					"frame": {
						"x": 1,
						"y": 1,
						"w": 16,
						"h": 16
					}
				},
				{
					"filename": "tower-302.png",
					"rotated": false,
					"trimmed": false,
					"sourceSize": {
						"w": 16,
						"h": 16
					},
					"spriteSourceSize": {
						"x": 0,
						"y": 0,
						"w": 16,
						"h": 16
					},
					"frame": {
						"x": 1,
						"y": 1,
						"w": 16,
						"h": 16
					}
				},
				{
					"filename": "tower-311.png",
					"rotated": false,
					"trimmed": false,
					"sourceSize": {
						"w": 16,
						"h": 16
					},
					"spriteSourceSize": {
						"x": 0,
						"y": 0,
						"w": 16,
						"h": 16
					},
					"frame": {
						"x": 1,
						"y": 1,
						"w": 16,
						"h": 16
					}
				},
				{
					"filename": "tower-303.png",
					"rotated": false,
					"trimmed": false,
					"sourceSize": {
						"w": 16,
						"h": 16
					},
					"spriteSourceSize": {
						"x": 0,
						"y": 0,
						"w": 16,
						"h": 16
					},
					"frame": {
						"x": 1,
						"y": 19,
						"w": 16,
						"h": 16
					}
				},
				{
					"filename": "tower-304.png",
					"rotated": false,
					"trimmed": false,
					"sourceSize": {
						"w": 16,
						"h": 16
					},
					"spriteSourceSize": {
						"x": 0,
						"y": 0,
						"w": 16,
						"h": 16
					},
					"frame": {
						"x": 1,
						"y": 37,
						"w": 16,
						"h": 16
					}
				},
				{
					"filename": "tower-308.png",
					"rotated": false,
					"trimmed": false,
					"sourceSize": {
						"w": 16,
						"h": 16
					},
					"spriteSourceSize": {
						"x": 0,
						"y": 0,
						"w": 16,
						"h": 16
					},
					"frame": {
						"x": 1,
						"y": 55,
						"w": 16,
						"h": 16
					}
				},
				{
					"filename": "tower-312.png",
					"rotated": false,
					"trimmed": false,
					"sourceSize": {
						"w": 16,
						"h": 16
					},
					"spriteSourceSize": {
						"x": 0,
						"y": 0,
						"w": 16,
						"h": 16
					},
					"frame": {
						"x": 1,
						"y": 73,
						"w": 16,
						"h": 16
					}
				},
				{
					"filename": "tower-306.png",
					"rotated": false,
					"trimmed": true,
					"sourceSize": {
						"w": 16,
						"h": 16
					},
					"spriteSourceSize": {
						"x": 0,
						"y": 2,
						"w": 16,
						"h": 14
					},
					"frame": {
						"x": 1,
						"y": 91,
						"w": 16,
						"h": 14
					}
				},
				{
					"filename": "tower-313.png",
					"rotated": false,
					"trimmed": true,
					"sourceSize": {
						"w": 16,
						"h": 16
					},
					"spriteSourceSize": {
						"x": 0,
						"y": 3,
						"w": 16,
						"h": 13
					},
					"frame": {
						"x": 1,
						"y": 107,
						"w": 16,
						"h": 13
					}
				},
				{
					"filename": "tower-307.png",
					"rotated": false,
					"trimmed": true,
					"sourceSize": {
						"w": 16,
						"h": 16
					},
					"spriteSourceSize": {
						"x": 0,
						"y": 4,
						"w": 16,
						"h": 12
					},
					"frame": {
						"x": 1,
						"y": 122,
						"w": 16,
						"h": 12
					}
				},
				{
					"filename": "tower-314.png",
					"rotated": false,
					"trimmed": true,
					"sourceSize": {
						"w": 16,
						"h": 16
					},
					"spriteSourceSize": {
						"x": 0,
						"y": 7,
						"w": 16,
						"h": 9
					},
					"frame": {
						"x": 1,
						"y": 136,
						"w": 16,
						"h": 9
					}
				},
				{
					"filename": "tower-315.png",
					"rotated": false,
					"trimmed": true,
					"sourceSize": {
						"w": 16,
						"h": 16
					},
					"spriteSourceSize": {
						"x": 0,
						"y": 9,
						"w": 16,
						"h": 7
					},
					"frame": {
						"x": 1,
						"y": 147,
						"w": 16,
						"h": 7
					}
				},
				{
					"filename": "tower-297.png",
					"rotated": false,
					"trimmed": true,
					"sourceSize": {
						"w": 16,
						"h": 16
					},
					"spriteSourceSize": {
						"x": 0,
						"y": 0,
						"w": 15,
						"h": 16
					},
					"frame": {
						"x": 1,
						"y": 156,
						"w": 15,
						"h": 16
					}
				},
				{
					"filename": "tower-298.png",
					"rotated": false,
					"trimmed": true,
					"sourceSize": {
						"w": 16,
						"h": 16
					},
					"spriteSourceSize": {
						"x": 0,
						"y": 0,
						"w": 15,
						"h": 16
					},
					"frame": {
						"x": 1,
						"y": 156,
						"w": 15,
						"h": 16
					}
				},
				{
					"filename": "tower-301.png",
					"rotated": false,
					"trimmed": true,
					"sourceSize": {
						"w": 16,
						"h": 16
					},
					"spriteSourceSize": {
						"x": 0,
						"y": 0,
						"w": 15,
						"h": 16
					},
					"frame": {
						"x": 1,
						"y": 174,
						"w": 15,
						"h": 16
					}
				},
				{
					"filename": "tower-305.png",
					"rotated": false,
					"trimmed": true,
					"sourceSize": {
						"w": 16,
						"h": 16
					},
					"spriteSourceSize": {
						"x": 0,
						"y": 0,
						"w": 15,
						"h": 16
					},
					"frame": {
						"x": 1,
						"y": 192,
						"w": 15,
						"h": 16
					}
				},
				{
					"filename": "tower-309.png",
					"rotated": false,
					"trimmed": true,
					"sourceSize": {
						"w": 16,
						"h": 16
					},
					"spriteSourceSize": {
						"x": 0,
						"y": 0,
						"w": 15,
						"h": 16
					},
					"frame": {
						"x": 1,
						"y": 210,
						"w": 15,
						"h": 16
					}
				},
				{
					"filename": "tower-310.png",
					"rotated": false,
					"trimmed": true,
					"sourceSize": {
						"w": 16,
						"h": 16
					},
					"spriteSourceSize": {
						"x": 0,
						"y": 0,
						"w": 14,
						"h": 16
					},
					"frame": {
						"x": 1,
						"y": 228,
						"w": 14,
						"h": 16
					}
				}
			]
		}
	],
	"meta": {
		"app": "https://www.codeandweb.com/texturepacker",
		"version": "3.0",
		"smartupdate": "$TexturePacker:SmartUpdate:c0183ed3b78954dc1f45c9f239a9ceba:1e3bc9dd3087e27b5e731557146f8e81:365b63dda70564996f0a94fcfa0ad655$"
	}
}
